tts_with_rvc/__init__.py
tts_with_rvc/inference_onnx.py
tts_with_rvc/lib/__init__.py
tts_with_rvc/lib/infer_pack/__init__.py
tts_with_rvc/lib/infer_pack/onnx_inference.py
tts_with_rvc/lib/infer_pack/modules/__init__.py
tts_with_rvc/lib/infer_pack/modules/F0Predictor/DioF0Predictor.py
tts_with_rvc/lib/infer_pack/modules/F0Predictor/F0Predictor.py
tts_with_rvc/lib/infer_pack/modules/F0Predictor/HarvestF0Predictor.py
tts_with_rvc/lib/infer_pack/modules/F0Predictor/PMF0Predictor.py
tts_with_rvc/lib/infer_pack/modules/F0Predictor/__init__.py
tts_with_rvc_onnx-0.1.9.4.dist-info/LICENSE
tts_with_rvc_onnx-0.1.9.4.dist-info/METADATA
tts_with_rvc_onnx-0.1.9.4.dist-info/WHEEL
tts_with_rvc_onnx-0.1.9.4.dist-info/top_level.txt
tts_with_rvc_onnx-0.1.9.4.dist-info/RECORD
